esse_BJS/__init__.py
esse_BJS/add.py
esse_BJS/ceil.py
esse_BJS/device_name.py
esse_BJS/div.py
esse_BJS/floor.py
esse_BJS/flr.py
esse_BJS/get_system.py
esse_BJS/hide_file.py
esse_BJS/logged_username.py
esse_BJS/main.py
esse_BJS/mod.py
esse_BJS/mult.py
esse_BJS/pow.py
esse_BJS/round.py
esse_BJS/spec_err.py
esse_BJS/sub.py
esse_bjs-0.1.1.dist-info/METADATA
esse_bjs-0.1.1.dist-info/WHEEL
esse_bjs-0.1.1.dist-info/RECORD
